hellocow/__init__.py
hellocow/__main__.py
hellocow/hellocow.py
hellocow-0.1.dist-info/LICENCE
hellocow-0.1.dist-info/METADATA
hellocow-0.1.dist-info/WHEEL
hellocow-0.1.dist-info/entry_points.txt
hellocow-0.1.dist-info/top_level.txt
hellocow-0.1.dist-info/RECORD
