Metadata-Version: 2.1
Name: hellocow
Version: 0.1
Summary: say hello to the cow
Home-page: https://github.com/ao/hellocow
Author: Andrew Odendaal
Author-email: a@ao.gl
License: UNKNOWN
Platform: UNKNOWN
Classifier: Programming Language :: Python :: 3
Classifier: License :: OSI Approved :: MIT License
Classifier: Operating System :: OS Independent
